nhpdf/__init__.py
nhpdf/nhpdf.py
nhpdf-1.8.dist-info/METADATA
nhpdf-1.8.dist-info/WHEEL
nhpdf-1.8.dist-info/entry_points.txt
nhpdf-1.8.dist-info/RECORD
