Metadata-Version: 2.4
Name: nhpdf
Version: 1.8
Summary: Download NHentai doujins as PDF
Project-URL: Homepage, https://github.com/Aze543/NhentaiDoujinToPDFMaker
Project-URL: Issues, https://github.com/Aze543/NhentaiDoujinToPDFMaker/issues
Author-email: Aze543 <eizen.9258437663@gmail.com>
Maintainer-email: Aze543 <eizen.9258437663@gmail.com>
License-Expression: MIT
Keywords: goon,pdf,scraper
Classifier: Development Status :: 4 - Beta
Classifier: Programming Language :: Python
Requires-Python: >=3.8
Requires-Dist: beautifulsoup4
Requires-Dist: cloudscraper
Requires-Dist: img2pdf
Requires-Dist: requests
